limin_talk/__init__.py
limin_talk/py.typed
limin_talk-0.2.0.dist-info/METADATA
limin_talk-0.2.0.dist-info/WHEEL
limin_talk-0.2.0.dist-info/top_level.txt
limin_talk-0.2.0.dist-info/RECORD
