Metadata-Version: 2.4
Name: limin-talk
Version: 0.2.0
Summary: A Python library for letting two LLMs talk to each other.
Author-email: Titanom Solutions <infrastructure@titanom.com>
Requires-Python: >=3.10
Requires-Dist: limin>=0.8.0
